LICENSE
MANIFEST.in
README.md
setup.cfg
setup.py
versioneer.py
python_Testing_Utilities/__init__.py
python_Testing_Utilities/_version.py
python_Testing_Utilities/assertMultiLineStringsEqual.py
python_Testing_Utilities/callService.py
python_Testing_Utilities/pythonObjCompare.py
python_Testing_Utilities.egg-info/PKG-INFO
python_Testing_Utilities.egg-info/SOURCES.txt
python_Testing_Utilities.egg-info/dependency_links.txt
python_Testing_Utilities.egg-info/not-zip-safe
python_Testing_Utilities.egg-info/requires.txt
python_Testing_Utilities.egg-info/top_level.txt
tests/test_assertMultiLineStringsEqual.py
tests/test_callService.py
tests/test_main.py
tests/test_pythonObjCompare.py